PyTestGame_2018-3.0.0.dist-info/DESCRIPTION.rst
PyTestGame_2018-3.0.0.dist-info/METADATA
PyTestGame_2018-3.0.0.dist-info/RECORD
PyTestGame_2018-3.0.0.dist-info/WHEEL
PyTestGame_2018-3.0.0.dist-info/metadata.json
PyTestGame_2018-3.0.0.dist-info/top_level.txt
wargame/__init__.py
wargame/abstractgameunit.py
wargame/attackoftheorcs.py
wargame/gameuniterror.py
wargame/gameutils.py
wargame/hut.py
wargame/knight.py
wargame/orcrider.py
