Metadata-Version: 2.0
Name: PyTestGame-2018
Version: 3.0.0
Summary: test pkg ignore
Home-page: https://testpypi.python.org/pypi/PyTestGame-2018/
Author: PythonTest
Author-email: wangshilei@loongson.cn
License: LICENSE.txt
Platform: UNKNOWN
